gen_text/__init__.py
gen_text/gentxt.py
gen_text/main.py
gen_text007-0.1.0.dist-info/METADATA
gen_text007-0.1.0.dist-info/WHEEL
gen_text007-0.1.0.dist-info/entry_points.txt
gen_text007-0.1.0.dist-info/RECORD
